aurastream_client/__init__.py
aurastream_client/api.py
aurastream_client/config.py
tests/__init__.py
tests/test_api.py
aurastream_client-0.1.0.dist-info/LICENSE.md
aurastream_client-0.1.0.dist-info/METADATA
aurastream_client-0.1.0.dist-info/WHEEL
aurastream_client-0.1.0.dist-info/top_level.txt
aurastream_client-0.1.0.dist-info/RECORD
