Metadata-Version: 2.1
Name: aurastream-client
Version: 0.1.0
Summary: An aurastream_client library for interacting with the AuraStream API
Author: Usama Ali
Author-email: usamaali012@gmail.com
Classifier: Development Status :: 3 - Alpha
Classifier: Intended Audience :: Developers
Classifier: Natural Language :: English
Classifier: Programming Language :: Python :: 3
Classifier: Programming Language :: Python :: 3.8
Classifier: Topic :: Software Development :: Libraries
Classifier: License :: OSI Approved :: MIT License
Requires-Python: >=3.8
License-File: LICENSE.md
Requires-Dist: requests (>=2.31.0)
Requires-Dist: python-dotenv (==1.0.0)
